samgob/.git
samgob/.gitmodules
samgob/README.md
samgob/__init__.py
samgob/dice_set.lang
samgob/errors.py
samgob/prelude.py.txt
samgob/goblang/.git
samgob/goblang/README.md
samgob/goblang/errors.py
samgob/goblang/example.lang
samgob/goblang/input.txt
samgob/goblang/read_lang.py
samgob/iterators/control_flow_iterator.py
samgob/iterators/file_word_parser.py
samgob-1.2.0.dist-info/METADATA
samgob-1.2.0.dist-info/WHEEL
samgob-1.2.0.dist-info/licenses/LICENSE
samgob-1.2.0.dist-info/RECORD
