Metadata-Version: 2.3
Name: samgob
Version: 1.2.0
Summary: A simple dice rolling languge embeded in python
Project-URL: Homepage, https://github.com/Mequam/samgob
Project-URL: Issues, https://github.com/Mequam/samgob/issues
Author-email: Mequam BlueSpark <blue9ja@gmail.com>
License-File: LICENSE
Classifier: License :: OSI Approved :: MIT License
Classifier: Operating System :: OS Independent
Classifier: Programming Language :: Python :: 3
Requires-Python: >=3.8
